{"spells":[{"name":"Minor Healing","level":1,"kind":"Heal","target":"Single","mana":"10","maxEffect":"12-20 HP","duration":"Instant","description":"Heals minor wounds.","school":"Alteration","source":"Vendor","era":"Classic","icon":99,"castMs":1500,"range":100},{"name":"Glimpse","level":2,"kind":"Utility Beneficial","target":"Self","mana":"5","maxEffect":"","duration":"12 Sec","description":"Allows you to see far off locations.","school":"Divination","source":"Vendor","era":"Classic","icon":106,"castMs":1500,"recastMs":12000},{"name":"Flame Lick","level":3,"kind":"Damage Over Time","target":"Single","mana":"12","maxEffect":"-17 HP/tick; -3 AC","duration":"36 Sec","description":"Deals damage over time and reduces AC.","school":"Evocation","source":"Vendor","era":"Classic","icon":51,"castMs":1500,"range":200,"resist":2},{"name":"Lull Animal","level":4,"kind":"Utility Detrimental","target":"Single","mana":"10","maxEffect":"Calm (max L30)","duration":"2 Min","description":"Calms animals up to level 30, reducing their agro radius.","school":"Alteration","source":"Vendor","era":"Classic","icon":39,"castMs":1500,"range":200,"resist":1},{"name":"Tangling Weeds","level":5,"kind":"Utility Detrimental","target":"Single","mana":"15","maxEffect":"Snare","duration":"18 Sec","description":"Slightly snares the enemy for a short duration.","school":"Alteration","source":"Vendor","era":"Classic","icon":5,"castMs":500,"recastMs":6000,"range":200,"resist":1},{"name":"Snare","level":6,"kind":"Utility Detrimental","target":"Single","mana":"15","maxEffect":"Snare","duration":"3 Min 54 Sec","description":"Snares the enemy for a short duration.","school":"Alteration","source":"Vendor","era":"Classic","icon":5,"castMs":2000,"range":200,"resist":1},{"name":"Skin like Wood","level":7,"kind":"HP Buffs","target":"Single","mana":"10","maxEffect":"+3 AC; +20 Max HP","duration":"27 Min","description":"Improves HP and AC by a minor amount.","school":"Abjuration","source":"Vendor","era":"Classic","icon":131,"castMs":3000,"recastMs":6000,"range":100},{"name":"Endure Fire","level":9,"kind":"Statistic Buffs","target":"Single","mana":"20","maxEffect":"+20 Fire Resist","duration":"27 Min","description":"Increases resistance to fire damage.","school":"Abjuration","source":"Vendor","era":"Classic","icon":52,"castMs":2500,"range":100},{"name":"Dance of the Fireflies","level":10,"kind":"Create Item","target":"Self","mana":"10","maxEffect":"Summon Item #10295","duration":"Instant","description":"Summons a minor light source.","school":"Conjuration","source":"Vendor","era":"Classic","icon":37,"castMs":3000,"recastMs":6000},{"name":"Hawk Eye","level":11,"kind":"Utility Beneficial","target":"Self","mana":"125","maxEffect":"","duration":"Instant","description":"Increases accuracy with a bow by 10%.","school":"Alteration","source":"Vendor","era":"Classic","icon":127,"castMs":3000},{"name":"Feet like Cat","level":12,"kind":"Statistic Buffs","target":"Single","mana":"40","maxEffect":"+18 AGI","duration":"36 Min","description":"Increases agility.","school":"Alteration","source":"Vendor","era":"Classic","icon":9,"castMs":5000,"range":100},{"name":"Cure Poison","level":13,"kind":"Heal","target":"Single","mana":"20","maxEffect":"Cure 1 Poison","duration":"Instant","description":"Removes poison counters from active poisons on the target.","school":"Alteration","source":"Vendor","era":"Classic","icon":42,"castMs":2000,"range":100},{"name":"Thistlecoat","level":13,"kind":"Utility Beneficial","target":"Self","mana":"25","maxEffect":"+5 AC","duration":"Instant","description":"Increases AC and damage shield.","school":"Abjuration","source":"Vendor","era":"Classic","icon":155,"castMs":2000,"resist":1},{"name":"Burst of Fire","level":14,"kind":"Direct Damage","target":"Single","mana":"7","maxEffect":"11-14 Dmg","duration":"Instant","description":"Deals fire damage to a target.","school":"Evocation","source":"Vendor","era":"Classic","icon":51,"castMs":1500,"range":200,"resist":2},{"name":"Camouflage","level":14,"kind":"Utility Beneficial","target":"Single","mana":"15","maxEffect":"","duration":"20 Min","description":"Makes your target invisible.","school":"Divination","source":"Vendor","era":"Classic","icon":18,"castMs":5000,"range":100},{"name":"Grasping Roots","level":15,"kind":"Utility Detrimental","target":"Single","mana":"35","maxEffect":"-10 Dmg; Root","duration":"48 Sec","description":"Roots your target in place.","school":"Alteration","source":"Vendor","era":"Classic","icon":117,"castMs":2000,"range":200,"resist":1},{"name":"Invoke Lightning","level":15,"kind":"Direct Damage","target":"Targeted AoE","mana":"32","maxEffect":"20-25 Dmg","duration":"Instant","description":"Strikes multiple targets for magic damage.","school":"Evocation","source":"Vendor","era":"Classic","icon":162,"castMs":2500,"recastMs":6000,"range":200,"resist":1},{"name":"Searing Arrow","level":15,"kind":"Direct Damage","target":"Single","mana":"35","maxEffect":"-58 Dmg; -29 HP/tick","duration":"1 tick","description":"Strikes a single target with a searing arrow, dealing 58 damage instantly and 29 damage 6 seconds later.","school":"Evocation","source":"Vendor","era":"Classic","icon":51,"castMs":500,"recastMs":10000,"range":200,"resist":2},{"name":"Light Healing","level":16,"kind":"Heal","target":"Single","mana":"28","maxEffect":"47-65 HP","duration":"Instant","description":"Heals light wounds.","school":"Alteration","source":"Vendor","era":"Classic","icon":99,"castMs":2000,"range":100},{"name":"Panic Animal","level":16,"kind":"Utility Detrimental","target":"Single","mana":"10","maxEffect":"Fear (max L52)","duration":"18 Sec","description":"Causes an animal up to level 52 to run in fear.","school":"Alteration","source":"Vendor","era":"Classic","icon":165,"castMs":2000,"range":200,"resist":1},{"name":"Ward Summoned","level":16,"kind":"Direct Damage","target":"Single","mana":"6","maxEffect":"6-14 Dmg","duration":"Instant","description":"Deals damage to summoned creatures.","school":"Evocation","source":"Vendor","era":"Classic","icon":153,"castMs":1500,"range":200,"resist":1},{"name":"Bind Sight","level":17,"kind":"Utility Beneficial","target":"Single","mana":"15","maxEffect":"","duration":"14 Min","description":"Binds your sight to the target, seeing what they see.","school":"Divination","source":"Vendor","era":"Classic","icon":44,"castMs":4000,"recastMs":10000,"range":10000},{"name":"Firefist","level":17,"kind":"Statistic Buffs","target":"Self","mana":"30","maxEffect":"+10 ATK","duration":"Instant","description":"Increases attack power by a minor amount.","school":"Evocation","source":"Vendor","era":"Classic","icon":2,"castMs":3500,"recastMs":7000},{"name":"Endure Cold","level":18,"kind":"Utility Beneficial","target":"Single","mana":"20","maxEffect":"+20 Cold Resist","duration":"27 Min","description":"Increases resistance to cold damage.","school":"Abjuration","source":"Vendor","era":"Classic","icon":57,"castMs":2500,"range":100},{"name":"Ignite","level":19,"kind":"Direct Damage","target":"Single","mana":"21","maxEffect":"38-46 Dmg","duration":"Instant","description":"Deals fire damage to a target.","school":"Evocation","source":"Vendor","era":"Classic","icon":51,"castMs":2000,"range":200,"resist":2},{"name":"Enduring Breath","level":20,"kind":"Utility Beneficial","target":"Single","mana":"35","maxEffect":"","duration":"27 Min","description":"Allows you to breathe underwater.","school":"Alteration","source":"Vendor","era":"Classic","icon":20,"castMs":4000,"range":100},{"name":"Skin like Rock","level":21,"kind":"HP Buffs","target":"Single","mana":"60","maxEffect":"+6 AC; +90 Max HP; 54-90 HP","duration":"27 Min","description":"Improves HP and AC by a light amount.","school":"Abjuration","source":"Vendor","era":"Classic","icon":131,"castMs":5000,"recastMs":8000,"range":100},{"name":"Cure Disease","level":22,"kind":"Heal","target":"Single","mana":"20","maxEffect":"Cure 1 Disease","duration":"Instant","description":"Removes disease counters from active diseases on the target.","school":"Alteration","source":"Vendor","era":"Classic","icon":41,"castMs":2000,"range":100},{"name":"Harmony","level":22,"kind":"Utility Detrimental","target":"Targeted AoE","mana":"25","maxEffect":"Calm (max L40)","duration":"2 Min","description":"Reduces the agro radius of all creatures around the target, up to level 40.","school":"Abjuration","source":"Vendor","era":"Classic","icon":39,"castMs":3000,"recastMs":12000,"range":200},{"name":"Shield of Thistles","level":24,"kind":"Utility Beneficial","target":"Single","mana":"40","maxEffect":"","duration":"15 Min","description":"Grants a damage shield to the target.","school":"Abjuration","source":"Vendor","era":"Classic","icon":155,"castMs":2500,"range":100,"resist":1},{"name":"Stinging Swarm","level":25,"kind":"Damage Over Time","target":"Single","mana":"71","maxEffect":"-42 HP/tick","duration":"54 Sec","description":"Summons a cloud of bees to damage the target over time.","school":"Conjuration","source":"Vendor","era":"Classic","icon":159,"castMs":3000,"range":250,"resist":1},{"name":"Flaming Arrow","level":26,"kind":"Direct Damage","target":"Target","mana":"55","maxEffect":"-102 Dmg; -51 HP/tick","duration":"6 seconds","description":"Hurls a burning arrow at your target, dealing 102 damage instantly and 51 damage 6 seconds later.","school":"Evocation","source":"Vendor","era":"Classic","icon":51,"castMs":500,"recastMs":10000,"range":200,"resist":2},{"name":"Strength of Earth","level":26,"kind":"Statistic Buffs","target":"Single","mana":"40","maxEffect":"+15 STR","duration":"27 Min","description":"Increases strength.","school":"Alteration","source":"Vendor","era":"Classic","icon":6,"castMs":5000,"range":100},{"name":"Eyes of the Cat","level":27,"kind":"Utility Beneficial","target":"Self","mana":"35","maxEffect":"","duration":"Instant","description":"Grants infravision, the ability to see in the dark.","school":"Divination","source":"Vendor","era":"Classic","icon":86,"castMs":3000,"recastMs":6000},{"name":"Healing","level":28,"kind":"Heal","target":"Target","mana":"65","maxEffect":"135-175 HP","duration":"Instant","description":"Heals the target for a moderate amount.","school":"Alteration","source":"Vendor","era":"Classic","icon":99,"castMs":2500,"range":100},{"name":"Spirit of Wolf","level":28,"kind":"Utility Beneficial","target":"Target","mana":"40","maxEffect":"Run Speed","duration":"36 Min","description":"Increases movement speed.","school":"Alteration","source":"Vendor","era":"Classic","icon":4,"castMs":4500,"range":100},{"name":"Riftwind's Protection","level":29,"kind":"Utility Beneficial","target":"Target","mana":"40","maxEffect":"","duration":"60 Min","description":"Increases AC and provides a damage shield.","school":"Abjuration","source":"Vendor","era":"Classic","icon":158,"castMs":3000,"range":150},{"name":"Barbcoat","level":30,"kind":"Utility Beneficial","target":"Self","mana":"50","maxEffect":"+10 AC","duration":"Instant","description":"Increases AC and provides a damage shield.","school":"Abjuration","source":"Vendor","era":"Classic","icon":155,"castMs":2000,"resist":1},{"name":"Cancel Magic","level":30,"kind":"Utility Detrimental","target":"Target","mana":"30","maxEffect":"","duration":"Instant","description":"Removes beneficial effects from the target.","school":"Abjuration","source":"Vendor","era":"Classic","icon":32,"castMs":3500,"range":200},{"name":"Calm Animal","level":31,"kind":"Utility Detrimental","target":"Target","mana":"45","maxEffect":"Calm (max L50)","duration":"42 Sec","description":"Reduces the agro radius of animals up to level 50.","school":"Alteration","source":"Vendor","era":"Classic","icon":39,"castMs":2500,"range":200,"resist":1},{"name":"See Invisible","level":32,"kind":"Utility Beneficial","target":"Target","mana":"25","maxEffect":"","duration":"27 Min","description":"Allows you to see invisible creatures.","school":"Divination","source":"Vendor","era":"Classic","icon":19,"castMs":2000,"range":100},{"name":"Dismiss Summoned","level":33,"kind":"Direct Damage","target":"Target","mana":"73","maxEffect":"226-244 Dmg","duration":"Instant","description":"Deals damage to summoned creatures.","school":"Evocation","source":"Vendor","era":"Classic","icon":153,"castMs":3000,"range":200,"resist":1},{"name":"Bramblecoat","level":34,"kind":"Utility Beneficial","target":"Self","mana":"75","maxEffect":"+15 AC","duration":"Instant","description":"Increases AC and provides a damage shield.","school":"Abjuration","source":"Vendor","era":"Classic","icon":155,"castMs":2000,"resist":1},{"name":"Levitate","level":35,"kind":"Utility Beneficial","target":"Target","mana":"30","maxEffect":"","duration":"20 Min 30 Sec","description":"Allows target to float.","school":"Alteration","source":"Vendor","era":"Classic","icon":80,"castMs":3000,"range":100},{"name":"Burning Arrow","level":36,"kind":"Direct Damage","target":"Target","mana":"85","maxEffect":"-155 Dmg; -78 HP/tick","duration":"Instant","description":"Hurls a burning arrow at your target, dealing 155 damage instantly and 78 damage 6 seconds later.","school":"Evocation","source":"Vendor","era":"Classic","icon":51,"castMs":500,"recastMs":10000,"range":200,"resist":2},{"name":"Call of Sky","level":36,"kind":"Utility Beneficial","target":"Self","mana":"50","maxEffect":"Procs: Call of Sky Strike","duration":"Instant","description":"Imparts power to your weapons, causing them to occasionally strike with additional power and stun.","school":"Alteration","source":"Vendor","era":"Classic","icon":104,"castMs":3500,"recastMs":6000},{"name":"Careless Lightning","level":37,"kind":"Direct Damage","target":"Targeted AoE","mana":"37","maxEffect":"96-105 Dmg","duration":"Instant","description":"Strikes multiple targets for magic damage.","school":"Evocation","source":"Vendor","era":"Classic","icon":162,"castMs":2500,"range":200,"resist":1},{"name":"Nature's Precision","level":37,"kind":"Statistic Buffs","target":"Self","mana":"50","maxEffect":"+15 ATK","duration":"Instant","description":"Increases attack power.","school":"Evocation","source":"Vendor","era":"Classic","icon":123,"castMs":3500,"recastMs":7000},{"name":"Greater Healing","level":38,"kind":"Heal","target":"Target","mana":"115","maxEffect":"280-350 HP","duration":"Instant","description":"Heals for a great amount.","school":"Alteration","source":"Vendor","era":"Classic","icon":99,"castMs":3000,"range":100},{"name":"Skin like Steel","level":38,"kind":"HP Buffs","target":"Target","mana":"100","maxEffect":"+8 AC; +100 Max HP; 74-100 HP","duration":"36 Min","description":"Increases AC and HP.","school":"Abjuration","source":"Vendor","era":"Classic","icon":131,"castMs":6000,"recastMs":9000,"range":100},{"name":"Harmony of Nature","level":39,"kind":"Detrimental","target":"Single","mana":"100","maxEffect":"Calm (max L65)","duration":"42 Sec","description":"Calms the savage spirit of almost any creature, making them less likely to attack. This spell works on creatures up to level 65, and only works outdoors.","school":"Abjuration","source":"","era":"Classic","icon":39,"castMs":2500,"range":200,"resist":1},{"name":"Swarm of Pain","level":40,"kind":"Damage Over Time","target":"Target","mana":"167","maxEffect":"-56 HP/tick","duration":"1 Min","description":"Summons a swarm of painful insects to deal damage to your target over time.","school":"Conjuration","source":"Vendor","era":"Classic","icon":159,"castMs":3000,"range":250,"resist":1},{"name":"Spirit of the Shrew","level":41,"kind":"Utility Beneficial","target":"Target","mana":"80","maxEffect":"Run Speed","duration":"36 Min","description":"Provides movement speed increase and ultravision.","school":"Alteration","source":"Vendor","era":"Classic","icon":4,"castMs":4500,"range":100},{"name":"Spikecoat","level":42,"kind":"Utility Beneficial","target":"Self","mana":"110","maxEffect":"+21 AC","duration":"Instant","description":"Increases AC and provides a damage shield.","school":"Abjuration","source":"Vendor","era":"Classic","icon":155,"castMs":2000,"resist":1},{"name":"Shield of Brambles","level":43,"kind":"Utility Beneficial","target":"Target","mana":"80","maxEffect":"","duration":"15 Min","description":"Provides a damage shield.","school":"Abjuration","source":"Vendor","era":"Classic","icon":155,"castMs":2500,"range":100,"resist":1},{"name":"Immolate","level":44,"kind":"Damage Over Time","target":"Target","mana":"72","maxEffect":"-67 HP/tick; -11 AC","duration":"48 Sec","description":"Deals fire damage over time.","school":"Evocation","source":"Vendor","era":"Classic","icon":51,"castMs":2500,"range":200,"resist":2},{"name":"Ensnaring Roots","level":45,"kind":"Utility Detrimental","target":"Target","mana":"60","maxEffect":"-31--60 Dmg; Root","duration":"1 Min 36 Sec","description":"Roots target.","school":"Alteration","source":"Vendor","era":"Classic","icon":117,"castMs":2500,"range":200,"resist":1},{"name":"Resist Fire","level":46,"kind":"Statistic Buffs","target":"Target","mana":"50","maxEffect":"+40 Fire Resist","duration":"36 Min","description":"Increases your resistance to fire damage.","school":"Abjuration","source":"Vendor","era":"Classic","icon":52,"castMs":4500,"range":100},{"name":"Scorching Arrow","level":46,"kind":"Direct Damage","target":"Target","mana":"100","maxEffect":"-210 Dmg; -105 HP/tick","duration":"Instant","description":"Hurls a scorching arrow at your target, dealing 210 damage instantly and 105 damage 6 seconds later.","school":"Evocation","source":"Vendor","era":"Classic","icon":51,"castMs":500,"recastMs":10000,"range":200,"resist":2},{"name":"Superior Camouflage","level":47,"kind":"Utility Beneficial","target":"Target","mana":"40","maxEffect":"","duration":"24 Min","description":"Grants longer lasting invisibility.","school":"Divination","source":"Vendor","era":"Classic","icon":34,"castMs":5000,"range":100},{"name":"Call of Earth","level":48,"kind":"Utility Beneficial","target":"Target","mana":"50","maxEffect":"+20 AC","duration":"60 Min","description":"Increases AC and grants a damage shield.","school":"Abjuration","source":"Vendor","era":"Classic","icon":158,"castMs":3500,"recastMs":6000,"range":150},{"name":"Wolf Form","level":48,"kind":"Utility Beneficial","target":"Self","mana":"60","maxEffect":"Illusion; Run Speed; +30 ATK","duration":"Instant","description":"Grants the form of a wolf, increasing movement speed, attack, and adjusting faction.","school":"Alteration","source":"Vendor","era":"Classic","icon":81,"castMs":4000,"recastMs":8000},{"name":"Call of Flame","level":49,"kind":"Direct Damage","target":"Target","mana":"106","maxEffect":"300 Dmg","duration":"Instant","description":"Inflicts fire damage to the target.","school":"Evocation","source":"Quest","era":"Classic","icon":51,"castMs":500,"recastMs":10000,"range":200,"resist":2},{"name":"Pack Shrew","level":49,"kind":"Utility Beneficial","target":"Group V1","mana":"320","maxEffect":"Run Speed","duration":"36 Min","description":"Grants movement speed and ultravision to your group.","school":"Alteration","source":"Vendor","era":"Classic","icon":4,"castMs":6000,"range":100},{"name":"Force of Nature","level":50,"kind":"Utility Beneficial","target":"Target","mana":"100","maxEffect":"+20 ATK","duration":"20 Min 30 Sec","description":"Increases health regeneration, damage shield, and attack.","school":"Alteration","source":"Vendor","era":"Classic","icon":158,"castMs":6000,"range":100},{"name":"Jolt","level":50,"kind":"Utility Detrimental","target":"Target","mana":"60","maxEffect":"","duration":"Instant","description":"Reduces your agro on the target.","school":"Alteration","source":"Vendor","era":"Classic","icon":40,"castMs":1500,"range":200,"resist":1}],"skills":[{"name":"Alcohol Tolerance","level":1,"trained":false,"cap50":"255","capPost":"255","category":"Miscellaneous"},{"name":"Fishing","level":1,"trained":false,"cap50":"200","capPost":"200","category":"Miscellaneous"},{"name":"Swimming","level":1,"trained":false,"cap50":"200","capPost":"200","category":"Miscellaneous"},{"name":"Forage","level":3,"trained":true,"cap50":"200","capPost":"200","category":"Miscellaneous"},{"name":"Hide","level":25,"trained":true,"cap50":"75","capPost":"75","category":"Miscellaneous"}],"aas":[{"name":"Hunter's Attack Power","ranks":"26","cost":"0","description":"This passive ability increases your attack power by 20 points. Requirements: level 8."},{"name":"Innate Called Shot","ranks":"1","cost":"0","description":"Grants the Ranger the ability to unleash a double bow shot on stationary targets. Requirements: level 1."},{"name":"Unbounded Strikethrough","ranks":"3","cost":"0","description":"This passive ability increases the chance you will strike through your opponent's active defenses, such as dodge, block, parry, and riposte, by 10/20/30%. Requirements: level 12."},{"name":"Weapon Mastery of the Scout","ranks":"3","cost":"3","description":"Increases the base damage of your archery attacks by 30/60/90%. Requirements: level 1. }"}]}